{
    "filename": "examples_1.v",
    "coq_project": "area-method",
    "vernac_cmds": [
        [
            "Require Import area_method.",
            "VernacRequire",
            "5c62f46411e4a320626f20a83b98394337ffc1f6"
        ],
        [
            "Theorem parallel_transitivity : forall A B C D E F : Point, A <> B -> on_parallel C D A B -> on_parallel E F C D -> parallel A B E F.",
            "VernacStartTheoremProof",
            "de336c2b1334785d5523fe0ba93085fe22e59c55"
        ],
        [
            "area_method.",
            "VernacExtend",
            "4588c212446e7ce16438c5e70340fee9f5d99151"
        ],
        [
            "Qed.",
            "VernacEndProof",
            "6eee6c55dea8e22a11abc36404343a43e520a888"
        ],
        [
            "Theorem parallel_pseudo_transitivity : forall A B C D E F : Point, A <> B -> on_parallel C D A B -> on_parallel E F A B -> parallel C D E F.",
            "VernacStartTheoremProof",
            "9f110c76a7f5fe0c7e0d538c5fd4e4d80294caf7"
        ],
        [
            "area_method.",
            "VernacExtend",
            "4588c212446e7ce16438c5e70340fee9f5d99151"
        ],
        [
            "Qed.",
            "VernacEndProof",
            "6eee6c55dea8e22a11abc36404343a43e520a888"
        ],
        [
            "Theorem parallellogram_second_parallel : forall A B C D : Point, on_parallel_d D C A B 1 -> parallel A C B D.",
            "VernacStartTheoremProof",
            "4bc6f86da60bcc9cb388e949554f9864514b573a"
        ],
        [
            "area_method.",
            "VernacExtend",
            "4588c212446e7ce16438c5e70340fee9f5d99151"
        ],
        [
            "Qed.",
            "VernacEndProof",
            "6eee6c55dea8e22a11abc36404343a43e520a888"
        ],
        [
            "Theorem parallellogram_construction : forall A B C D I : Point, is_midpoint I A C -> on_line_d D I B (-(1)) -> parallel C D A B.",
            "VernacStartTheoremProof",
            "2728f494d3aff8fa98fb0a837d08786b6954f923"
        ],
        [
            "area_method.",
            "VernacExtend",
            "4588c212446e7ce16438c5e70340fee9f5d99151"
        ],
        [
            "Qed.",
            "VernacEndProof",
            "6eee6c55dea8e22a11abc36404343a43e520a888"
        ],
        [
            "Lemma example_construction_simplification: forall A B C D E F G Line_3_b Line_6_b, on_line C A B -> on_parallel Line_3_b C A D -> inter_ll E C Line_3_b B D -> on_parallel Line_6_b C F A -> inter_ll G C Line_6_b F B -> parallel E G D F.",
            "VernacStartTheoremProof",
            "7737f87b09970320f78526ffad206d3d1ad80aef"
        ],
        [
            "area_method.",
            "VernacExtend",
            "4588c212446e7ce16438c5e70340fee9f5d99151"
        ],
        [
            "Qed.",
            "VernacEndProof",
            "6eee6c55dea8e22a11abc36404343a43e520a888"
        ],
        [
            "Theorem parallellogram_construction_2 : forall A B C D I : Point, is_midpoint I A C -> on_line_d D I B (-(1)) -> parallel C D A B /\\ parallel A D B C.",
            "VernacStartTheoremProof",
            "1ee1d7933d1766856e21201e9891b7810beae978"
        ],
        [
            "area_method.",
            "VernacExtend",
            "4588c212446e7ce16438c5e70340fee9f5d99151"
        ],
        [
            "Qed.",
            "VernacEndProof",
            "6eee6c55dea8e22a11abc36404343a43e520a888"
        ],
        [
            "Theorem parallelogram_midpoint : forall A B C D I : Point, on_parallel_d D C A B (0-1) -> inter_ll I A C B D -> A<>C -> A<>I -> parallel A I A C -> A ** I / A**C = 1 / 2.",
            "VernacStartTheoremProof",
            "7ae5dbd2aa1073167912ee5908cf9f2520fea28b"
        ],
        [
            "am_before_field.",
            "VernacExtend",
            "5ea7c344a8f41fc4a140b8e737f2821ccd297a4c"
        ],
        [
            "intuition.",
            "VernacExtend",
            "ebd9388eeb482972743f9cce5cbddbd85ca5bdfd"
        ],
        [
            "Ffield.",
            "VernacExtend",
            "27905c4a7456d052c4e8d396f0099fe95e61d621"
        ],
        [
            "Qed.",
            "VernacEndProof",
            "6eee6c55dea8e22a11abc36404343a43e520a888"
        ],
        [
            "Theorem Prop51Hartsshornebis : forall A B C D E : Point, ~ Col D A C -> ~ Col A B C -> is_midpoint D A B -> is_midpoint E A C -> parallel D E B C -> B <> C -> D ** E / B ** C = 1 / 2.",
            "VernacStartTheoremProof",
            "2d4144718a57c56d84d63f17475ad7aed5ce3c96"
        ],
        [
            "area_method.",
            "VernacExtend",
            "4588c212446e7ce16438c5e70340fee9f5d99151"
        ],
        [
            "Qed.",
            "VernacEndProof",
            "6eee6c55dea8e22a11abc36404343a43e520a888"
        ]
    ],
    "proofs": [
        {
            "name": "parallel_transitivity",
            "line_nb": 1,
            "steps": [
                {
                    "command": [
                        "area_method.",
                        "VernacExtend",
                        "4588c212446e7ce16438c5e70340fee9f5d99151"
                    ]
                },
                {
                    "command": [
                        "Qed.",
                        "VernacEndProof",
                        "6eee6c55dea8e22a11abc36404343a43e520a888"
                    ]
                }
            ]
        },
        {
            "name": "parallel_pseudo_transitivity",
            "line_nb": 4,
            "steps": [
                {
                    "command": [
                        "area_method.",
                        "VernacExtend",
                        "4588c212446e7ce16438c5e70340fee9f5d99151"
                    ]
                },
                {
                    "command": [
                        "Qed.",
                        "VernacEndProof",
                        "6eee6c55dea8e22a11abc36404343a43e520a888"
                    ]
                }
            ]
        },
        {
            "name": "parallellogram_second_parallel",
            "line_nb": 7,
            "steps": [
                {
                    "command": [
                        "area_method.",
                        "VernacExtend",
                        "4588c212446e7ce16438c5e70340fee9f5d99151"
                    ]
                },
                {
                    "command": [
                        "Qed.",
                        "VernacEndProof",
                        "6eee6c55dea8e22a11abc36404343a43e520a888"
                    ]
                }
            ]
        },
        {
            "name": "parallellogram_construction",
            "line_nb": 10,
            "steps": [
                {
                    "command": [
                        "area_method.",
                        "VernacExtend",
                        "4588c212446e7ce16438c5e70340fee9f5d99151"
                    ]
                },
                {
                    "command": [
                        "Qed.",
                        "VernacEndProof",
                        "6eee6c55dea8e22a11abc36404343a43e520a888"
                    ]
                }
            ]
        },
        {
            "name": "example_construction_simplification",
            "line_nb": 13,
            "steps": [
                {
                    "command": [
                        "area_method.",
                        "VernacExtend",
                        "4588c212446e7ce16438c5e70340fee9f5d99151"
                    ]
                },
                {
                    "command": [
                        "Qed.",
                        "VernacEndProof",
                        "6eee6c55dea8e22a11abc36404343a43e520a888"
                    ]
                }
            ]
        },
        {
            "name": "parallellogram_construction_2",
            "line_nb": 16,
            "steps": [
                {
                    "command": [
                        "area_method.",
                        "VernacExtend",
                        "4588c212446e7ce16438c5e70340fee9f5d99151"
                    ]
                },
                {
                    "command": [
                        "Qed.",
                        "VernacEndProof",
                        "6eee6c55dea8e22a11abc36404343a43e520a888"
                    ]
                }
            ]
        },
        {
            "name": "parallelogram_midpoint",
            "line_nb": 19,
            "steps": [
                {
                    "command": [
                        "am_before_field.",
                        "VernacExtend",
                        "5ea7c344a8f41fc4a140b8e737f2821ccd297a4c"
                    ]
                },
                {
                    "command": [
                        "intuition.",
                        "VernacExtend",
                        "ebd9388eeb482972743f9cce5cbddbd85ca5bdfd"
                    ]
                },
                {
                    "command": [
                        "Ffield.",
                        "VernacExtend",
                        "27905c4a7456d052c4e8d396f0099fe95e61d621"
                    ]
                },
                {
                    "command": [
                        "Qed.",
                        "VernacEndProof",
                        "6eee6c55dea8e22a11abc36404343a43e520a888"
                    ]
                }
            ]
        },
        {
            "name": "Prop51Hartsshornebis",
            "line_nb": 24,
            "steps": [
                {
                    "command": [
                        "area_method.",
                        "VernacExtend",
                        "4588c212446e7ce16438c5e70340fee9f5d99151"
                    ]
                },
                {
                    "command": [
                        "Qed.",
                        "VernacEndProof",
                        "6eee6c55dea8e22a11abc36404343a43e520a888"
                    ]
                }
            ]
        }
    ]
}