{
    "filename": "RELATIONS/Noetherian.v",
    "coq_project": "concat",
    "vernac_cmds": [
        [
            "Require Import Relations.",
            "VernacRequire",
            "e1c772579226dab59a43a462d5506decc27ae0bb"
        ],
        [
            "Set Implicit Arguments.",
            "VernacSetOption",
            "9e84ff8896f028601d8aded48c1d4aebe60aa584"
        ],
        [
            "Unset Strict Implicit.",
            "VernacUnsetOption",
            "2842adaf6959318f2042805935c46f513bdc0348"
        ],
        [
            "Section Noether.",
            "VernacBeginSection",
            "28b225a3759b857bd1550c66b06323b9f3a35309"
        ],
        [
            "Variable U : Type.",
            "VernacAssumption",
            "eb05258af3da16894daf420a97be779934a15d7e"
        ],
        [
            "Variable R : Relation U.",
            "VernacAssumption",
            "2ee80cb0443e24b8aaf7ac473030c6c8ca487ca3"
        ],
        [
            "Inductive noetherian : U -> Prop := Build_noetherian : forall x : U, (forall y : U, R x y -> noetherian y) -> noetherian x.",
            "VernacInductive",
            "ff52aa50725217af8e21a4345485793a80135e4a"
        ],
        [
            "Definition Noetherian : Prop := forall x : U, noetherian x.",
            "VernacDefinition",
            "686b15cd43514b77f17527e780994f583af90e28"
        ],
        [
            "End Noether.",
            "VernacEndSegment",
            "c0940f67aa207765a7917681b8796782453af26a"
        ],
        [
            "Hint Resolve Build_noetherian.",
            "VernacHints",
            "d2fabc97f1cbe117842f28937710e36915d402a8"
        ],
        [
            "Theorem Noetherian_contains_Noetherian : forall (U : Type) (R R' : Relation U), Noetherian R -> Contains R R' -> Noetherian R'.",
            "VernacStartTheoremProof",
            "98f424340c2942ac7699d1525d57cf775c9ccaf9"
        ],
        [
            "unfold Noetherian at 2 in |- *.",
            "VernacExtend",
            "f09d3f6f1ba24f896bf3578c817aee734b8fe835"
        ],
        [
            "intros U R R' H' H'0 x.",
            "VernacExtend",
            "86d1f20ea35e6919751dcfbb19fbc2902d0e09ce"
        ],
        [
            "elim H' with x; auto.",
            "VernacExtend",
            "17fd67d3d75a16714e5b34da4aa191e9bc3c4025"
        ],
        [
            "Qed.",
            "VernacEndProof",
            "6eee6c55dea8e22a11abc36404343a43e520a888"
        ]
    ],
    "proofs": [
        {
            "name": "Noetherian_contains_Noetherian",
            "line_nb": 10,
            "steps": [
                {
                    "command": [
                        "unfold Noetherian at 2 in |- *.",
                        "VernacExtend",
                        "f09d3f6f1ba24f896bf3578c817aee734b8fe835"
                    ]
                },
                {
                    "command": [
                        "intros U R R' H' H'0 x.",
                        "VernacExtend",
                        "86d1f20ea35e6919751dcfbb19fbc2902d0e09ce"
                    ]
                },
                {
                    "command": [
                        "elim H' with x; auto.",
                        "VernacExtend",
                        "17fd67d3d75a16714e5b34da4aa191e9bc3c4025"
                    ]
                },
                {
                    "command": [
                        "Qed.",
                        "VernacEndProof",
                        "6eee6c55dea8e22a11abc36404343a43e520a888"
                    ]
                }
            ]
        }
    ]
}