{
    "filename": "invprel1.v",
    "coq_project": "otway-rees",
    "vernac_cmds": [
        [
            "Require Import securite.",
            "VernacRequire",
            "79f028bb1437551f02489992d37fa72b1c6f2e29"
        ],
        [
            "Lemma POinvprel1 : forall (l l0 : list C) (k k0 k1 k2 : K) (c c0 c1 c2 : C) (d d0 d1 d2 d3 d4 d5 d6 d7 d8 d9 d10 d11 d12 d13 d14 d15 d16 d17 d18 d19 d20 : D), inv0 (ABSI (MBNaKab d7 d8 d9 k0) (MANbKabCaCb d4 d5 d6 k c c0) (MABNaNbKeyK d d0 d1 d2 d3) l) -> inv1 (ABSI (MBNaKab d7 d8 d9 k0) (MANbKabCaCb d4 d5 d6 k c c0) (MABNaNbKeyK d d0 d1 d2 d3) l) -> invP (ABSI (MBNaKab d7 d8 d9 k0) (MANbKabCaCb d4 d5 d6 k c c0) (MABNaNbKeyK d d0 d1 d2 d3) l) -> rel1 (ABSI (MBNaKab d7 d8 d9 k0) (MANbKabCaCb d4 d5 d6 k c c0) (MABNaNbKeyK d d0 d1 d2 d3) l) (ABSI (MBNaKab d18 d19 d20 k2) (MANbKabCaCb d15 d16 d17 k1 c1 c2) (MABNaNbKeyK d10 d11 d12 d13 d14) l0) -> invP (ABSI (MBNaKab d18 d19 d20 k2) (MANbKabCaCb d15 d16 d17 k1 c1 c2) (MABNaNbKeyK d10 d11 d12 d13 d14) l0).",
            "VernacStartTheoremProof",
            "33e89177f0b94573e8c8f68e3215d2f7da28c5d7"
        ],
        [
            "do 32 intro.",
            "VernacExtend",
            "39710ad74ca200107f422220c09716edee522c35"
        ],
        [
            "unfold invP, rel1 in |- *; intros Inv0 Inv1 know_Kab and1.",
            "VernacExtend",
            "4b0ee5ad32587bb6896fb2facc01b910a0f3d0d2"
        ],
        [
            "elim and1; intros eq_l0 t1.",
            "VernacExtend",
            "9c167a5f86d7c99595f8b61704a2f2599d875dc3"
        ],
        [
            "clear Inv0 Inv1 and1 t1.",
            "VernacExtend",
            "859ccae472e74e2ee581da4eb6eaf18bf55d878f"
        ],
        [
            "rewrite eq_l0.",
            "VernacExtend",
            "e7f54cf2b5676aaa2d717b61f80f830328812a52"
        ],
        [
            "unfold quad in |- *.",
            "VernacExtend",
            "fd209c884c703d8691723141c0f8f8599541f6c2"
        ],
        [
            "apply D2.",
            "VernacExtend",
            "9594f7b31e8422866c2cf6cabaf3749915c39f61"
        ],
        [
            "simpl in |- *.",
            "VernacExtend",
            "1b93169f4cf876d207c1fab22a2347202ab48d85"
        ],
        [
            "repeat apply C2 || apply C3 || apply C4.",
            "VernacExtend",
            "f83b07d1e85b13662406591fda67be2523a6a6ef"
        ],
        [
            "apply D1; assumption.",
            "VernacExtend",
            "f827019a0240ff77a753d85d52d1fe547593105e"
        ],
        [
            "discriminate.",
            "VernacExtend",
            "66ca81b65e1a53372a2515fdfdd2a6b0677cb9c8"
        ],
        [
            "discriminate.",
            "VernacExtend",
            "66ca81b65e1a53372a2515fdfdd2a6b0677cb9c8"
        ],
        [
            "discriminate.",
            "VernacExtend",
            "66ca81b65e1a53372a2515fdfdd2a6b0677cb9c8"
        ],
        [
            "discriminate.",
            "VernacExtend",
            "66ca81b65e1a53372a2515fdfdd2a6b0677cb9c8"
        ],
        [
            "discriminate.",
            "VernacExtend",
            "66ca81b65e1a53372a2515fdfdd2a6b0677cb9c8"
        ],
        [
            "discriminate.",
            "VernacExtend",
            "66ca81b65e1a53372a2515fdfdd2a6b0677cb9c8"
        ],
        [
            "discriminate.",
            "VernacExtend",
            "66ca81b65e1a53372a2515fdfdd2a6b0677cb9c8"
        ],
        [
            "discriminate.",
            "VernacExtend",
            "66ca81b65e1a53372a2515fdfdd2a6b0677cb9c8"
        ],
        [
            "discriminate.",
            "VernacExtend",
            "66ca81b65e1a53372a2515fdfdd2a6b0677cb9c8"
        ],
        [
            "discriminate.",
            "VernacExtend",
            "66ca81b65e1a53372a2515fdfdd2a6b0677cb9c8"
        ],
        [
            "discriminate.",
            "VernacExtend",
            "66ca81b65e1a53372a2515fdfdd2a6b0677cb9c8"
        ],
        [
            "discriminate.",
            "VernacExtend",
            "66ca81b65e1a53372a2515fdfdd2a6b0677cb9c8"
        ],
        [
            "discriminate.",
            "VernacExtend",
            "66ca81b65e1a53372a2515fdfdd2a6b0677cb9c8"
        ],
        [
            "discriminate.",
            "VernacExtend",
            "66ca81b65e1a53372a2515fdfdd2a6b0677cb9c8"
        ],
        [
            "Qed.",
            "VernacEndProof",
            "6eee6c55dea8e22a11abc36404343a43e520a888"
        ]
    ],
    "proofs": [
        {
            "name": "POinvprel1",
            "line_nb": 1,
            "steps": [
                {
                    "command": [
                        "do 32 intro.",
                        "VernacExtend",
                        "39710ad74ca200107f422220c09716edee522c35"
                    ]
                },
                {
                    "command": [
                        "unfold invP, rel1 in |- *; intros Inv0 Inv1 know_Kab and1.",
                        "VernacExtend",
                        "4b0ee5ad32587bb6896fb2facc01b910a0f3d0d2"
                    ]
                },
                {
                    "command": [
                        "elim and1; intros eq_l0 t1.",
                        "VernacExtend",
                        "9c167a5f86d7c99595f8b61704a2f2599d875dc3"
                    ]
                },
                {
                    "command": [
                        "clear Inv0 Inv1 and1 t1.",
                        "VernacExtend",
                        "859ccae472e74e2ee581da4eb6eaf18bf55d878f"
                    ]
                },
                {
                    "command": [
                        "rewrite eq_l0.",
                        "VernacExtend",
                        "e7f54cf2b5676aaa2d717b61f80f830328812a52"
                    ]
                },
                {
                    "command": [
                        "unfold quad in |- *.",
                        "VernacExtend",
                        "fd209c884c703d8691723141c0f8f8599541f6c2"
                    ]
                },
                {
                    "command": [
                        "apply D2.",
                        "VernacExtend",
                        "9594f7b31e8422866c2cf6cabaf3749915c39f61"
                    ]
                },
                {
                    "command": [
                        "simpl in |- *.",
                        "VernacExtend",
                        "1b93169f4cf876d207c1fab22a2347202ab48d85"
                    ]
                },
                {
                    "command": [
                        "repeat apply C2 || apply C3 || apply C4.",
                        "VernacExtend",
                        "f83b07d1e85b13662406591fda67be2523a6a6ef"
                    ]
                },
                {
                    "command": [
                        "apply D1; assumption.",
                        "VernacExtend",
                        "f827019a0240ff77a753d85d52d1fe547593105e"
                    ]
                },
                {
                    "command": [
                        "discriminate.",
                        "VernacExtend",
                        "66ca81b65e1a53372a2515fdfdd2a6b0677cb9c8"
                    ]
                },
                {
                    "command": [
                        "discriminate.",
                        "VernacExtend",
                        "66ca81b65e1a53372a2515fdfdd2a6b0677cb9c8"
                    ]
                },
                {
                    "command": [
                        "discriminate.",
                        "VernacExtend",
                        "66ca81b65e1a53372a2515fdfdd2a6b0677cb9c8"
                    ]
                },
                {
                    "command": [
                        "discriminate.",
                        "VernacExtend",
                        "66ca81b65e1a53372a2515fdfdd2a6b0677cb9c8"
                    ]
                },
                {
                    "command": [
                        "discriminate.",
                        "VernacExtend",
                        "66ca81b65e1a53372a2515fdfdd2a6b0677cb9c8"
                    ]
                },
                {
                    "command": [
                        "discriminate.",
                        "VernacExtend",
                        "66ca81b65e1a53372a2515fdfdd2a6b0677cb9c8"
                    ]
                },
                {
                    "command": [
                        "discriminate.",
                        "VernacExtend",
                        "66ca81b65e1a53372a2515fdfdd2a6b0677cb9c8"
                    ]
                },
                {
                    "command": [
                        "discriminate.",
                        "VernacExtend",
                        "66ca81b65e1a53372a2515fdfdd2a6b0677cb9c8"
                    ]
                },
                {
                    "command": [
                        "discriminate.",
                        "VernacExtend",
                        "66ca81b65e1a53372a2515fdfdd2a6b0677cb9c8"
                    ]
                },
                {
                    "command": [
                        "discriminate.",
                        "VernacExtend",
                        "66ca81b65e1a53372a2515fdfdd2a6b0677cb9c8"
                    ]
                },
                {
                    "command": [
                        "discriminate.",
                        "VernacExtend",
                        "66ca81b65e1a53372a2515fdfdd2a6b0677cb9c8"
                    ]
                },
                {
                    "command": [
                        "discriminate.",
                        "VernacExtend",
                        "66ca81b65e1a53372a2515fdfdd2a6b0677cb9c8"
                    ]
                },
                {
                    "command": [
                        "discriminate.",
                        "VernacExtend",
                        "66ca81b65e1a53372a2515fdfdd2a6b0677cb9c8"
                    ]
                },
                {
                    "command": [
                        "discriminate.",
                        "VernacExtend",
                        "66ca81b65e1a53372a2515fdfdd2a6b0677cb9c8"
                    ]
                },
                {
                    "command": [
                        "Qed.",
                        "VernacEndProof",
                        "6eee6c55dea8e22a11abc36404343a43e520a888"
                    ]
                }
            ]
        }
    ]
}