{
    "filename": "Z_succ_pred.v",
    "coq_project": "chinese",
    "vernac_cmds": [
        [
            "Require Export Arith.",
            "VernacRequire",
            "70e550b9603a7aa23f63274fffcc443ce7c8f433"
        ],
        [
            "Require Export Zbase.",
            "VernacRequire",
            "90086057a1e27e47013d08b1052f4c5fbd9802d9"
        ],
        [
            "Definition succZ (x : Z) := match x return Z with | OZ => IZ | pos n => pos (S n) | neg n => match n return Z with | O => OZ | S m => neg m end end.",
            "VernacDefinition",
            "4e63c2d7ecd82c04ab69a0382fa76ef3dc41bb15"
        ],
        [
            "Definition predZ (x : Z) := match x return Z with | OZ => neg 0 | pos n => match n return Z with | O => OZ | S m => pos m end | neg n => neg (S n) end.",
            "VernacDefinition",
            "7db6d0896c338e016667730990613aa507aaded3"
        ],
        [
            "Lemma pred_succZ : forall x : Z, predZ (succZ x) = x.",
            "VernacStartTheoremProof",
            "f6cf032fa0c26a4615fe7d0303c948ac0d5ee2b6"
        ],
        [
            "intros; pattern x in |- *; elim x.",
            "VernacExtend",
            "05e5cb2e9012f88e70e56537453a8f46114f883d"
        ],
        [
            "simpl in |- *; reflexivity.",
            "VernacExtend",
            "929257572def0332e6c079b4ed3a916720086e3a"
        ],
        [
            "simpl in |- *; reflexivity.",
            "VernacExtend",
            "929257572def0332e6c079b4ed3a916720086e3a"
        ],
        [
            "intros; elim n.",
            "VernacExtend",
            "e1c732204fc2c9d9d3a3b0af2ef59699d18744bc"
        ],
        [
            "simpl in |- *; reflexivity.",
            "VernacExtend",
            "929257572def0332e6c079b4ed3a916720086e3a"
        ],
        [
            "intros; simpl in |- *; reflexivity.",
            "VernacExtend",
            "854cdc9d9e97990c301aa41eba8e57e0e92b6986"
        ],
        [
            "Qed.",
            "VernacEndProof",
            "6eee6c55dea8e22a11abc36404343a43e520a888"
        ],
        [
            "Lemma succ_predZ : forall x : Z, succZ (predZ x) = x.",
            "VernacStartTheoremProof",
            "17397e682d37c9a6a73e64acb8dbf1ec6fe687bb"
        ],
        [
            "intros; pattern x in |- *; elim x.",
            "VernacExtend",
            "05e5cb2e9012f88e70e56537453a8f46114f883d"
        ],
        [
            "simpl in |- *; reflexivity.",
            "VernacExtend",
            "929257572def0332e6c079b4ed3a916720086e3a"
        ],
        [
            "intros; elim n.",
            "VernacExtend",
            "e1c732204fc2c9d9d3a3b0af2ef59699d18744bc"
        ],
        [
            "simpl in |- *; reflexivity.",
            "VernacExtend",
            "929257572def0332e6c079b4ed3a916720086e3a"
        ],
        [
            "intros; simpl in |- *; reflexivity.",
            "VernacExtend",
            "854cdc9d9e97990c301aa41eba8e57e0e92b6986"
        ],
        [
            "simpl in |- *; reflexivity.",
            "VernacExtend",
            "929257572def0332e6c079b4ed3a916720086e3a"
        ],
        [
            "Qed.",
            "VernacEndProof",
            "6eee6c55dea8e22a11abc36404343a43e520a888"
        ],
        [
            "Lemma succ_pred_pred_succZ : forall x : Z, succZ (predZ x) = predZ (succZ x).",
            "VernacStartTheoremProof",
            "36f572979b736d3cab6a0fdddd9d98f7e579d4b4"
        ],
        [
            "intros; rewrite (pred_succZ x); exact (succ_predZ x).",
            "VernacExtend",
            "d9ad1b1a95cc27cf8c759b2fdf74e846b5261018"
        ],
        [
            "Qed.",
            "VernacEndProof",
            "6eee6c55dea8e22a11abc36404343a43e520a888"
        ],
        [
            "Lemma tech_pred_posZ : forall n : nat, 0 < n -> predZ (pos n) = pos (pred n).",
            "VernacStartTheoremProof",
            "d8159ab39e7dc805811b834f941dfb0a93806caa"
        ],
        [
            "intro; elim n; intro.",
            "VernacExtend",
            "93c2a889756b3b95d1263d72bb91fda9ad091741"
        ],
        [
            "elim (lt_n_O 0); exact H.",
            "VernacExtend",
            "733d0cc3fdcfca7b5360530fe13cc8a6fdc72b22"
        ],
        [
            "intros; simpl in |- *; reflexivity.",
            "VernacExtend",
            "854cdc9d9e97990c301aa41eba8e57e0e92b6986"
        ],
        [
            "Qed.",
            "VernacEndProof",
            "6eee6c55dea8e22a11abc36404343a43e520a888"
        ],
        [
            "Lemma tech_succ_posOZ : forall n : nat, succZ (posOZ n) = pos n.",
            "VernacStartTheoremProof",
            "b4aaf3915cee8112112964d97e48a37a22169cb4"
        ],
        [
            "intros; elim n; simpl in |- *; reflexivity; simpl in |- *; reflexivity.",
            "VernacExtend",
            "b1ea92f6aec6e1d7b5c0fa793d87442abef771be"
        ],
        [
            "Qed.",
            "VernacEndProof",
            "6eee6c55dea8e22a11abc36404343a43e520a888"
        ]
    ],
    "proofs": [
        {
            "name": "pred_succZ",
            "line_nb": 4,
            "steps": [
                {
                    "command": [
                        "intros; pattern x in |- *; elim x.",
                        "VernacExtend",
                        "05e5cb2e9012f88e70e56537453a8f46114f883d"
                    ]
                },
                {
                    "command": [
                        "simpl in |- *; reflexivity.",
                        "VernacExtend",
                        "929257572def0332e6c079b4ed3a916720086e3a"
                    ]
                },
                {
                    "command": [
                        "simpl in |- *; reflexivity.",
                        "VernacExtend",
                        "929257572def0332e6c079b4ed3a916720086e3a"
                    ]
                },
                {
                    "command": [
                        "intros; elim n.",
                        "VernacExtend",
                        "e1c732204fc2c9d9d3a3b0af2ef59699d18744bc"
                    ]
                },
                {
                    "command": [
                        "simpl in |- *; reflexivity.",
                        "VernacExtend",
                        "929257572def0332e6c079b4ed3a916720086e3a"
                    ]
                },
                {
                    "command": [
                        "intros; simpl in |- *; reflexivity.",
                        "VernacExtend",
                        "854cdc9d9e97990c301aa41eba8e57e0e92b6986"
                    ]
                },
                {
                    "command": [
                        "Qed.",
                        "VernacEndProof",
                        "6eee6c55dea8e22a11abc36404343a43e520a888"
                    ]
                }
            ]
        },
        {
            "name": "succ_predZ",
            "line_nb": 12,
            "steps": [
                {
                    "command": [
                        "intros; pattern x in |- *; elim x.",
                        "VernacExtend",
                        "05e5cb2e9012f88e70e56537453a8f46114f883d"
                    ]
                },
                {
                    "command": [
                        "simpl in |- *; reflexivity.",
                        "VernacExtend",
                        "929257572def0332e6c079b4ed3a916720086e3a"
                    ]
                },
                {
                    "command": [
                        "intros; elim n.",
                        "VernacExtend",
                        "e1c732204fc2c9d9d3a3b0af2ef59699d18744bc"
                    ]
                },
                {
                    "command": [
                        "simpl in |- *; reflexivity.",
                        "VernacExtend",
                        "929257572def0332e6c079b4ed3a916720086e3a"
                    ]
                },
                {
                    "command": [
                        "intros; simpl in |- *; reflexivity.",
                        "VernacExtend",
                        "854cdc9d9e97990c301aa41eba8e57e0e92b6986"
                    ]
                },
                {
                    "command": [
                        "simpl in |- *; reflexivity.",
                        "VernacExtend",
                        "929257572def0332e6c079b4ed3a916720086e3a"
                    ]
                },
                {
                    "command": [
                        "Qed.",
                        "VernacEndProof",
                        "6eee6c55dea8e22a11abc36404343a43e520a888"
                    ]
                }
            ]
        },
        {
            "name": "succ_pred_pred_succZ",
            "line_nb": 20,
            "steps": [
                {
                    "command": [
                        "intros; rewrite (pred_succZ x); exact (succ_predZ x).",
                        "VernacExtend",
                        "d9ad1b1a95cc27cf8c759b2fdf74e846b5261018"
                    ]
                },
                {
                    "command": [
                        "Qed.",
                        "VernacEndProof",
                        "6eee6c55dea8e22a11abc36404343a43e520a888"
                    ]
                }
            ]
        },
        {
            "name": "tech_pred_posZ",
            "line_nb": 23,
            "steps": [
                {
                    "command": [
                        "intro; elim n; intro.",
                        "VernacExtend",
                        "93c2a889756b3b95d1263d72bb91fda9ad091741"
                    ]
                },
                {
                    "command": [
                        "elim (lt_n_O 0); exact H.",
                        "VernacExtend",
                        "733d0cc3fdcfca7b5360530fe13cc8a6fdc72b22"
                    ]
                },
                {
                    "command": [
                        "intros; simpl in |- *; reflexivity.",
                        "VernacExtend",
                        "854cdc9d9e97990c301aa41eba8e57e0e92b6986"
                    ]
                },
                {
                    "command": [
                        "Qed.",
                        "VernacEndProof",
                        "6eee6c55dea8e22a11abc36404343a43e520a888"
                    ]
                }
            ]
        },
        {
            "name": "tech_succ_posOZ",
            "line_nb": 28,
            "steps": [
                {
                    "command": [
                        "intros; elim n; simpl in |- *; reflexivity; simpl in |- *; reflexivity.",
                        "VernacExtend",
                        "b1ea92f6aec6e1d7b5c0fa793d87442abef771be"
                    ]
                },
                {
                    "command": [
                        "Qed.",
                        "VernacEndProof",
                        "6eee6c55dea8e22a11abc36404343a43e520a888"
                    ]
                }
            ]
        }
    ]
}