{
    "filename": "Setminus_fact.v",
    "coq_project": "schroeder",
    "vernac_cmds": [
        [
            "Require Import Ensembles.",
            "VernacRequire",
            "63f80d6be2b42bad6c3542a86c69acf401d90a4a"
        ],
        [
            "Section Contravariance_of_Setminus.",
            "VernacBeginSection",
            "2e3e32910e41aec0054373dbbdca1c965e2fe37e"
        ],
        [
            "Variable U : Type.",
            "VernacAssumption",
            "eb05258af3da16894daf420a97be779934a15d7e"
        ],
        [
            "Lemma Setminus_contravariant : forall A B B' : Ensemble U, Included U B' B -> Included U (Setminus U A B) (Setminus U A B').",
            "VernacStartTheoremProof",
            "3cd4950ef890e52b797067d3643804933248273d"
        ],
        [
            "intros A B B' B'_Included_B; unfold Setminus in |- *.",
            "VernacExtend",
            "8cd7cf1b8d6805a069603fb85c953c9371e9b1f2"
        ],
        [
            "red in |- *; intros x x_in_B.",
            "VernacExtend",
            "654f7427114078052945b71a70a42cad88bfc429"
        ],
        [
            "elim x_in_B; intros x_in_A x_in_nonB.",
            "VernacExtend",
            "020f4797f7376d0c8c598f615b58da0c1c9983d2"
        ],
        [
            "split.",
            "VernacExtend",
            "55abc140132bd88981001ac656020469a8d503eb"
        ],
        [
            "assumption.",
            "VernacExtend",
            "41f0308313ff87e6ab2782f90d6021ec4b55d932"
        ],
        [
            "red in |- *; intro x_in_B'.",
            "VernacExtend",
            "982ba6a58dffc52c069e4201b71591d5eb60d048"
        ],
        [
            "apply x_in_nonB.",
            "VernacExtend",
            "d14dec378b953503f5d42e6fea41fcc38862da1f"
        ],
        [
            "apply B'_Included_B.",
            "VernacExtend",
            "a3b0bf89c0d3ec3c315b3441056de863d79c653b"
        ],
        [
            "assumption.",
            "VernacExtend",
            "41f0308313ff87e6ab2782f90d6021ec4b55d932"
        ],
        [
            "Qed.",
            "VernacEndProof",
            "6eee6c55dea8e22a11abc36404343a43e520a888"
        ],
        [
            "End Contravariance_of_Setminus.",
            "VernacEndSegment",
            "87902955ffb2474604a3a8ecf9e861565a759598"
        ]
    ],
    "proofs": [
        {
            "name": "Setminus_contravariant",
            "line_nb": 3,
            "steps": [
                {
                    "command": [
                        "intros A B B' B'_Included_B; unfold Setminus in |- *.",
                        "VernacExtend",
                        "8cd7cf1b8d6805a069603fb85c953c9371e9b1f2"
                    ]
                },
                {
                    "command": [
                        "red in |- *; intros x x_in_B.",
                        "VernacExtend",
                        "654f7427114078052945b71a70a42cad88bfc429"
                    ]
                },
                {
                    "command": [
                        "elim x_in_B; intros x_in_A x_in_nonB.",
                        "VernacExtend",
                        "020f4797f7376d0c8c598f615b58da0c1c9983d2"
                    ]
                },
                {
                    "command": [
                        "split.",
                        "VernacExtend",
                        "55abc140132bd88981001ac656020469a8d503eb"
                    ]
                },
                {
                    "command": [
                        "assumption.",
                        "VernacExtend",
                        "41f0308313ff87e6ab2782f90d6021ec4b55d932"
                    ]
                },
                {
                    "command": [
                        "red in |- *; intro x_in_B'.",
                        "VernacExtend",
                        "982ba6a58dffc52c069e4201b71591d5eb60d048"
                    ]
                },
                {
                    "command": [
                        "apply x_in_nonB.",
                        "VernacExtend",
                        "d14dec378b953503f5d42e6fea41fcc38862da1f"
                    ]
                },
                {
                    "command": [
                        "apply B'_Included_B.",
                        "VernacExtend",
                        "a3b0bf89c0d3ec3c315b3441056de863d79c653b"
                    ]
                },
                {
                    "command": [
                        "assumption.",
                        "VernacExtend",
                        "41f0308313ff87e6ab2782f90d6021ec4b55d932"
                    ]
                },
                {
                    "command": [
                        "Qed.",
                        "VernacEndProof",
                        "6eee6c55dea8e22a11abc36404343a43e520a888"
                    ]
                }
            ]
        }
    ]
}